revcat/__init__.py
revcat/cli.py
revcat/common.py
revcat/v1/__init__.py
revcat/v1/customers.py
revcat/v1/entitlements.py
revcat/v1/extensions.py
revcat-0.1.7.dist-info/METADATA
revcat-0.1.7.dist-info/WHEEL
revcat-0.1.7.dist-info/entry_points.txt
revcat-0.1.7.dist-info/licenses/LICENSE
revcat-0.1.7.dist-info/RECORD
