Metadata-Version: 2.4
Name: revcat
Version: 0.1.7
Summary: Unofficial RevenueCat CLI for Python
Project-URL: source, https://github.com/sealambda/revenuecat-cli
Project-URL: issues, https://github.com/sealambda/revenuecat-cli/issues
Author-email: Sealambda <hello@sealambda.com>
License-Expression: MIT
License-File: LICENSE
Keywords: cli,revenuecat
Classifier: Development Status :: 4 - Beta
Classifier: Environment :: Console
Classifier: Intended Audience :: Developers
Classifier: License :: OSI Approved :: MIT License
Classifier: Operating System :: OS Independent
Classifier: Programming Language :: Python :: 3.9
Classifier: Programming Language :: Python :: 3.10
Classifier: Programming Language :: Python :: 3.11
Classifier: Programming Language :: Python :: 3.12
Classifier: Programming Language :: Python :: 3.13
Classifier: Topic :: Utilities
Requires-Python: >=3.9
Requires-Dist: requests>=2.32.3
Requires-Dist: typer>=0.15.1
